{"barcode":"1235418790239","display_name":"არაყი/ცელსი LUX/1ლ+2XL","unit":"1ლ","image_url":"https://wolt-menu-images-cdn.wolt.com/menu-images/63f8bffc06bbde74b8eec406/bac1a7b2-7343-11ee-ac82-eed73505972e_1235418790239.jpg","category_slug":"alcohol","parent_category_slug":"drinks","offers":[{"store_slug":"magniti","store_name":"Magniti","brand_id":"magniti","name":"არაყი/ცელსი LUX/1ლ+2XL","barcode":"1235418790239","image_url":"https://wolt-menu-images-cdn.wolt.com/menu-images/63f8bffc06bbde74b8eec406/bac1a7b2-7343-11ee-ac82-eed73505972e_1235418790239.jpg","unit":"1ლ","category_slug":"alcohol","parent_category_slug":"drinks","original_price":45.95,"sale_price":45.95,"discount_percent":0.0,"is_on_sale":false,"effective_price":45.95,"chain_rank":7}],"summary":{"avg_price":45.95,"min_price":45.95,"max_price":45.95,"price_spread":0.0,"store_count":1,"promo_count":0,"promo_rate":0.0,"cheapest_brand_id":"magniti","top_brand_id":"magniti","model_source":"static-export-live-retail-prices"},"observed_source":"heuristic"}