{"barcode":"3104710300140","display_name":"მდოგვი დიჟონის /BORNIER/ 370გრ","unit":"370გრ","image_url":"https://static.agrohub.lemon.do/Agrohub_files/2baab770-c05a-4c92-8a90-9d432470d1ad_Thumb.jpg","category_slug":"canned_goods","parent_category_slug":"groceries","offers":[{"store_slug":"agrohub","store_name":"Agrohub","brand_id":"agrohub","name":"მდოგვი დიჟონის /BORNIER/ 370გრ","barcode":"3104710300140","image_url":"https://static.agrohub.lemon.do/Agrohub_files/2baab770-c05a-4c92-8a90-9d432470d1ad_Thumb.jpg","unit":"370გრ","category_slug":"canned_goods","parent_category_slug":"groceries","original_price":17.95,"sale_price":13.4,"discount_percent":25.35,"is_on_sale":true,"effective_price":13.4,"chain_rank":4}],"summary":{"avg_price":13.4,"min_price":13.4,"max_price":13.4,"price_spread":0.0,"store_count":1,"promo_count":1,"promo_rate":100.0,"cheapest_brand_id":"agrohub","top_brand_id":"agrohub","model_source":"static-export-live-retail-prices"},"observed_source":"heuristic"}