{"barcode":"4008258324011","display_name":"SEEBERGER-ქლიავის ჩირი","unit":null,"image_url":"https://static.agrohub.lemon.do/Agrohub_files/5880d03e-3184-4c0b-b395-7ab965053d8d_Thumb.jpg","category_slug":"private_label","parent_category_slug":"groceries","offers":[{"store_slug":"goodwill","store_name":"Goodwill","brand_id":"goodwill","name":"SEEBERGER-ქლიავის ჩირი","barcode":"4008258324011","image_url":"https://static.agrohub.lemon.do/Agrohub_files/5880d03e-3184-4c0b-b395-7ab965053d8d_Thumb.jpg","unit":null,"category_slug":"private_label","parent_category_slug":"groceries","original_price":12.35,"sale_price":12.35,"discount_percent":0.0,"is_on_sale":false,"effective_price":12.35,"chain_rank":2},{"store_slug":"agrohub","store_name":"Agrohub","brand_id":"agrohub","name":"SEEBERGER-ქლიავის ჩირი","barcode":"4008258324011","image_url":"https://static.agrohub.lemon.do/Agrohub_files/5880d03e-3184-4c0b-b395-7ab965053d8d_Thumb.jpg","unit":null,"category_slug":"private_label","parent_category_slug":"groceries","original_price":12.95,"sale_price":12.95,"discount_percent":0.0,"is_on_sale":false,"effective_price":12.95,"chain_rank":4}],"summary":{"avg_price":12.65,"min_price":12.35,"max_price":12.95,"price_spread":0.6,"store_count":2,"promo_count":0,"promo_rate":0.0,"cheapest_brand_id":"goodwill","top_brand_id":"agrohub","model_source":"static-export-live-retail-prices"},"observed_source":"heuristic"}