{"barcode":"4037719065002","display_name":"კანფეტი / C&H / უშაქრო / შერეული ხილის წვეთები / 175 გრ","unit":"175 გრ","image_url":"https://static.agrohub.lemon.do/Agrohub_files/772fb17b-c0fb-4c7b-9289-8224d8b76694_Thumb.jpg","category_slug":"vegetables_fruits","parent_category_slug":"vegetables_fruits","offers":[{"store_slug":"agrohub","store_name":"Agrohub","brand_id":"agrohub","name":"კანფეტი / C&H / უშაქრო / შერეული ხილის წვეთები / 175 გრ","barcode":"4037719065002","image_url":"https://static.agrohub.lemon.do/Agrohub_files/772fb17b-c0fb-4c7b-9289-8224d8b76694_Thumb.jpg","unit":"175 გრ","category_slug":"vegetables_fruits","parent_category_slug":"vegetables_fruits","original_price":13.6,"sale_price":13.6,"discount_percent":0.0,"is_on_sale":false,"effective_price":13.6,"chain_rank":4}],"summary":{"avg_price":13.6,"min_price":13.6,"max_price":13.6,"price_spread":0.0,"store_count":1,"promo_count":0,"promo_rate":0.0,"cheapest_brand_id":"agrohub","top_brand_id":"agrohub","model_source":"static-export-live-retail-prices"},"observed_source":"heuristic"}