{"barcode":"4037719068195","display_name":"C&H -კანფეტი კოლას წვეთები 175გრ","unit":"175გრ","image_url":"https://static.goodwill.ge/Goodwill_files/d3bb08d7-5463-4586-ab37-d3519c2835d5_Thumb.jpg","category_slug":"candy","parent_category_slug":"sweets","offers":[{"store_slug":"spar","store_name":"Spar","brand_id":"spar","name":"C&H -კანფეტი კოლას წვეთები 175გრ","barcode":"4037719068195","image_url":"https://static.goodwill.ge/Goodwill_files/d3bb08d7-5463-4586-ab37-d3519c2835d5_Thumb.jpg","unit":"175გრ","category_slug":"candy","parent_category_slug":"sweets","original_price":11.59,"sale_price":11.59,"discount_percent":0.0,"is_on_sale":false,"effective_price":11.59,"chain_rank":3}],"summary":{"avg_price":11.59,"min_price":11.59,"max_price":11.59,"price_spread":0.0,"store_count":1,"promo_count":0,"promo_rate":0.0,"cheapest_brand_id":"spar","top_brand_id":"spar","model_source":"static-export-live-retail-prices"},"observed_source":"heuristic"}