{"barcode":"4311501399149","display_name":"ლიმონის წვენი ორგანული /EDEKA/ 200 მლ","unit":"200 მლ","image_url":"https://static.agrohub.lemon.do/Agrohub_files/41cd5f36-b2e5-482e-888b-2c9322ba90fb_Thumb.jpg","category_slug":"juice_nectar","parent_category_slug":"drinks","offers":[{"store_slug":"agrohub","store_name":"Agrohub","brand_id":"agrohub","name":"ლიმონის წვენი ორგანული /EDEKA/ 200 მლ","barcode":"4311501399149","image_url":"https://static.agrohub.lemon.do/Agrohub_files/41cd5f36-b2e5-482e-888b-2c9322ba90fb_Thumb.jpg","unit":"200 მლ","category_slug":"juice_nectar","parent_category_slug":"drinks","original_price":2.95,"sale_price":2.95,"discount_percent":0.0,"is_on_sale":false,"effective_price":2.95,"chain_rank":4}],"summary":{"avg_price":2.95,"min_price":2.95,"max_price":2.95,"price_spread":0.0,"store_count":1,"promo_count":0,"promo_rate":0.0,"cheapest_brand_id":"agrohub","top_brand_id":"agrohub","model_source":"static-export-live-retail-prices"},"observed_source":"heuristic"}