{"barcode":"4311501016770","display_name":"G+G მიწისთხილის კარაქი კრემოვანი","unit":null,"image_url":"https://static.goodwill.ge/Goodwill_files/20084feb-272e-4ddf-ba35-c51142dce4bb_Thumb.jpg","category_slug":"vegetables_fruits","parent_category_slug":"vegetables_fruits","offers":[{"store_slug":"goodwill","store_name":"Goodwill","brand_id":"goodwill","name":"G+G მიწისთხილის კარაქი კრემოვანი","barcode":"4311501016770","image_url":"https://static.goodwill.ge/Goodwill_files/20084feb-272e-4ddf-ba35-c51142dce4bb_Thumb.jpg","unit":null,"category_slug":"vegetables_fruits","parent_category_slug":"vegetables_fruits","original_price":15.45,"sale_price":15.45,"discount_percent":0.0,"is_on_sale":false,"effective_price":15.45,"chain_rank":2}],"summary":{"avg_price":15.45,"min_price":15.45,"max_price":15.45,"price_spread":0.0,"store_count":1,"promo_count":0,"promo_rate":0.0,"cheapest_brand_id":"goodwill","top_brand_id":"goodwill","model_source":"static-export-live-retail-prices"},"observed_source":"heuristic"}