{"barcode":"4602248009492","display_name":"წიწიბურა 4*62.5გრ /იარმარკა/ 400გრ","unit":"62.5გრ","image_url":"https://static.agrohub.lemon.do/Agrohub_files/cbe4de0c-d90f-4ef1-951b-8979aa5ec4cc_Thumb.jpg","category_slug":"canned_goods","parent_category_slug":"groceries","offers":[{"store_slug":"agrohub","store_name":"Agrohub","brand_id":"agrohub","name":"წიწიბურა 4*62.5გრ /იარმარკა/ 400გრ","barcode":"4602248009492","image_url":"https://static.agrohub.lemon.do/Agrohub_files/cbe4de0c-d90f-4ef1-951b-8979aa5ec4cc_Thumb.jpg","unit":"62.5გრ","category_slug":"canned_goods","parent_category_slug":"groceries","original_price":6.4,"sale_price":6.4,"discount_percent":0.0,"is_on_sale":false,"effective_price":6.4,"chain_rank":4},{"store_slug":"carrefour","store_name":"Carrefour","brand_id":"carrefour","name":"წიწიბურა 4*62.5გრ /იარმარკა/ 400გრ","barcode":"4602248009492","image_url":"https://static.agrohub.lemon.do/Agrohub_files/cbe4de0c-d90f-4ef1-951b-8979aa5ec4cc_Thumb.jpg","unit":"62.5გრ","category_slug":"canned_goods","parent_category_slug":"groceries","original_price":6.85,"sale_price":6.85,"discount_percent":0.0,"is_on_sale":false,"effective_price":6.85,"chain_rank":1}],"summary":{"avg_price":6.62,"min_price":6.4,"max_price":6.85,"price_spread":0.45,"store_count":2,"promo_count":0,"promo_rate":0.0,"cheapest_brand_id":"agrohub","top_brand_id":"agrohub","model_source":"static-export-live-retail-prices"},"observed_source":"heuristic"}