{"barcode":"4605246009006","display_name":"ჩაი შავი \"გრინფილდი\" როიალ ელგრეი 2გრ*20ც","unit":"2გრ","image_url":"https://cdn.2nabiji.ge/products/chai-shavi-grinphildi-roial-elgrei.webp","category_slug":"cereals","parent_category_slug":"hot_drinks","offers":[{"store_slug":"2nabiji","store_name":"2 Nabiji","brand_id":"2nabiji","name":"ჩაი შავი \"გრინფილდი\" როიალ ელგრეი 2გრ*20ც","barcode":"4605246009006","image_url":"https://cdn.2nabiji.ge/products/chai-shavi-grinphildi-roial-elgrei.webp","unit":"2გრ","category_slug":"cereals","parent_category_slug":"hot_drinks","original_price":7.25,"sale_price":2.99,"discount_percent":58.76,"is_on_sale":true,"effective_price":2.99,"chain_rank":8}],"summary":{"avg_price":2.99,"min_price":2.99,"max_price":2.99,"price_spread":0.0,"store_count":1,"promo_count":1,"promo_rate":100.0,"cheapest_brand_id":"2nabiji","top_brand_id":"2nabiji","model_source":"static-export-live-retail-prices"},"observed_source":"heuristic"}