{"barcode":"4606180010882","display_name":"ხორცის კონსერვი/მოშუშული ღორის ხორცი უმაღლესი ხარისხი/338 გრ","unit":"338 გრ","image_url":"https://imageproxy.wolt.com/assets/69bd363f7d97abbe0eb93967","category_slug":"meat_fish","parent_category_slug":"meat_fish","offers":[{"store_slug":"nikora","store_name":"Nikora","brand_id":"nikora","name":"ხორცის კონსერვი/მოშუშული ღორის ხორცი უმაღლესი ხარისხი/338 გრ","barcode":"4606180010882","image_url":"https://imageproxy.wolt.com/assets/69bd363f7d97abbe0eb93967","unit":"338 გრ","category_slug":"meat_fish","parent_category_slug":"meat_fish","original_price":8.95,"sale_price":8.95,"discount_percent":0.0,"is_on_sale":false,"effective_price":8.95,"chain_rank":6},{"store_slug":"spar","store_name":"Spar","brand_id":"spar","name":"ხორცის კონსერვი/მოშუშული ღორის ხორცი უმაღლესი ხარისხი/338 გრ","barcode":"4606180010882","image_url":"https://imageproxy.wolt.com/assets/69bd363f7d97abbe0eb93967","unit":"338 გრ","category_slug":"meat_fish","parent_category_slug":"meat_fish","original_price":10.5,"sale_price":10.5,"discount_percent":0.0,"is_on_sale":false,"effective_price":10.5,"chain_rank":3}],"summary":{"avg_price":9.72,"min_price":8.95,"max_price":10.5,"price_spread":1.55,"store_count":2,"promo_count":0,"promo_rate":0.0,"cheapest_brand_id":"nikora","top_brand_id":"nikora","model_source":"static-export-live-retail-prices"},"observed_source":"heuristic"}