{"barcode":"4607052661843","display_name":"მწვანე წიწ.ფქვGLUTEN FREE500გ/4607052661843 1ც","unit":"500გ","image_url":"https://wolt-menu-images-cdn.wolt.com/menu-images/5f6b69ba5d07dca217bd3620/cbdcb178-5b09-11ef-925d-66e029be181b_314533.jpg","category_slug":"cereals","parent_category_slug":"groceries","offers":[{"store_slug":"carrefour","store_name":"Carrefour","brand_id":"carrefour","name":"მწვანე წიწ.ფქვGLUTEN FREE500გ/4607052661843 1ც","barcode":"4607052661843","image_url":"https://wolt-menu-images-cdn.wolt.com/menu-images/5f6b69ba5d07dca217bd3620/cbdcb178-5b09-11ef-925d-66e029be181b_314533.jpg","unit":"500გ","category_slug":"cereals","parent_category_slug":"groceries","original_price":14.45,"sale_price":14.45,"discount_percent":0.0,"is_on_sale":false,"effective_price":14.45,"chain_rank":1}],"summary":{"avg_price":14.45,"min_price":14.45,"max_price":14.45,"price_spread":0.0,"store_count":1,"promo_count":0,"promo_rate":0.0,"cheapest_brand_id":"carrefour","top_brand_id":"carrefour","model_source":"static-export-live-retail-prices"},"observed_source":"heuristic"}