{"barcode":"4751001585954","display_name":"კონსერვი თევზის \"სტელა მარისი\" ტრესკას ღვიძლი 121გრ","unit":"121გრ","image_url":"https://static.agrohub.lemon.do/Agrohub_files/4fd7bfaa-5766-463e-a932-a88140446fa3_Thumb.jpeg","category_slug":"meat_fish","parent_category_slug":"meat_fish","offers":[{"store_slug":"2nabiji","store_name":"Kalata","brand_id":"2nabiji","name":"კონსერვი თევზის \"სტელა მარისი\" ტრესკას ღვიძლი 121გრ","barcode":"4751001585954","image_url":"https://static.agrohub.lemon.do/Agrohub_files/4fd7bfaa-5766-463e-a932-a88140446fa3_Thumb.jpeg","unit":"121გრ","category_slug":"meat_fish","parent_category_slug":"meat_fish","original_price":7.5,"sale_price":7.5,"discount_percent":0.0,"is_on_sale":false,"effective_price":7.5,"chain_rank":8}],"summary":{"avg_price":7.5,"min_price":7.5,"max_price":7.5,"price_spread":0.0,"store_count":1,"promo_count":0,"promo_rate":0.0,"cheapest_brand_id":"2nabiji","top_brand_id":"2nabiji","model_source":"static-export-live-retail-prices"},"observed_source":"heuristic"}