{"barcode":"4820154727143","display_name":"ნაყინი სუპერ შოკოლადი 100% /რუდე/","unit":null,"image_url":"https://wolt-menu-images-cdn.wolt.com/menu-images/5f6b69ba5d07dca217bd3620/88688b3e-5b08-11ef-9355-5e639c7fb4de_149914.jpg","category_slug":"frozen","parent_category_slug":"frozen","offers":[{"store_slug":"carrefour","store_name":"Carrefour","brand_id":"carrefour","name":"ნაყინი სუპერ შოკოლადი 100% /რუდე/","barcode":"4820154727143","image_url":"https://wolt-menu-images-cdn.wolt.com/menu-images/5f6b69ba5d07dca217bd3620/88688b3e-5b08-11ef-9355-5e639c7fb4de_149914.jpg","unit":null,"category_slug":"frozen","parent_category_slug":"frozen","original_price":17.95,"sale_price":17.95,"discount_percent":0.0,"is_on_sale":false,"effective_price":17.95,"chain_rank":1}],"summary":{"avg_price":17.95,"min_price":17.95,"max_price":17.95,"price_spread":0.0,"store_count":1,"promo_count":0,"promo_rate":0.0,"cheapest_brand_id":"carrefour","top_brand_id":"carrefour","model_source":"static-export-live-retail-prices"},"observed_source":"heuristic"}