{"barcode":"4820008125446","display_name":"ფანტელი სიმინდის \"სტარტი\" შოკოლადის ბალიშებით 500გრ","unit":"500გრ","image_url":"https://static.goodwill.ge/Goodwill_files/f71ae1c5-7117-4bf1-b99c-d1bf4fbc9dac_Thumb.jpg","category_slug":"candy","parent_category_slug":"sweets","offers":[{"store_slug":"2nabiji","store_name":"2 Nabiji","brand_id":"2nabiji","name":"ფანტელი სიმინდის \"სტარტი\" შოკოლადის ბალიშებით 500გრ","barcode":"4820008125446","image_url":"https://static.goodwill.ge/Goodwill_files/f71ae1c5-7117-4bf1-b99c-d1bf4fbc9dac_Thumb.jpg","unit":"500გრ","category_slug":"candy","parent_category_slug":"sweets","original_price":6.99,"sale_price":6.99,"discount_percent":0.0,"is_on_sale":false,"effective_price":6.99,"chain_rank":8},{"store_slug":"goodwill","store_name":"Goodwill","brand_id":"goodwill","name":"ფანტელი სიმინდის \"სტარტი\" შოკოლადის ბალიშებით 500გრ","barcode":"4820008125446","image_url":"https://static.goodwill.ge/Goodwill_files/f71ae1c5-7117-4bf1-b99c-d1bf4fbc9dac_Thumb.jpg","unit":"500გრ","category_slug":"candy","parent_category_slug":"sweets","original_price":14.25,"sale_price":14.25,"discount_percent":0.0,"is_on_sale":false,"effective_price":14.25,"chain_rank":2}],"summary":{"avg_price":10.62,"min_price":6.99,"max_price":14.25,"price_spread":7.26,"store_count":2,"promo_count":0,"promo_rate":0.0,"cheapest_brand_id":"2nabiji","top_brand_id":"2nabiji","model_source":"static-export-live-retail-prices"},"observed_source":"heuristic"}