{"barcode":"4823058337241","display_name":"ცელოფანი /ფინო კვების პროდუქტის შესაფუთი/ 20მ","unit":" 20მ","image_url":"https://static.agrohub.lemon.do/Agrohub_files/84922df7-b5f1-4f5f-8aa8-7154f6414d6f_Thumb.jpg","category_slug":"private_label","parent_category_slug":"groceries","offers":[{"store_slug":"magniti","store_name":"Magniti","brand_id":"magniti","name":"ცელოფანი /ფინო კვების პროდუქტის შესაფუთი/ 20მ","barcode":"4823058337241","image_url":"https://static.agrohub.lemon.do/Agrohub_files/84922df7-b5f1-4f5f-8aa8-7154f6414d6f_Thumb.jpg","unit":" 20მ","category_slug":"private_label","parent_category_slug":"groceries","original_price":3.95,"sale_price":3.95,"discount_percent":0.0,"is_on_sale":false,"effective_price":3.95,"chain_rank":7},{"store_slug":"spar","store_name":"Spar","brand_id":"spar","name":"ცელოფანი /ფინო კვების პროდუქტის შესაფუთი/ 20მ","barcode":"4823058337241","image_url":"https://static.agrohub.lemon.do/Agrohub_files/84922df7-b5f1-4f5f-8aa8-7154f6414d6f_Thumb.jpg","unit":" 20მ","category_slug":"private_label","parent_category_slug":"groceries","original_price":4.2,"sale_price":4.2,"discount_percent":0.0,"is_on_sale":false,"effective_price":4.2,"chain_rank":3}],"summary":{"avg_price":4.08,"min_price":3.95,"max_price":4.2,"price_spread":0.25,"store_count":2,"promo_count":0,"promo_rate":0.0,"cheapest_brand_id":"magniti","top_brand_id":"magniti","model_source":"static-export-live-retail-prices"},"observed_source":"heuristic"}