{"barcode":"4860108990704","display_name":"ჰიმალაის მარილი მსხვილი 140გრ","unit":"140გრ","image_url":"https://static.agrohub.lemon.do/Agrohub_files/b8fe8468-dfec-42f7-8325-9510c13c2e5f_Thumb.jpg","category_slug":"canned_goods","parent_category_slug":"groceries","offers":[{"store_slug":"agrohub","store_name":"Agrohub","brand_id":"agrohub","name":"ჰიმალაის მარილი მსხვილი 140გრ","barcode":"4860108990704","image_url":"https://static.agrohub.lemon.do/Agrohub_files/b8fe8468-dfec-42f7-8325-9510c13c2e5f_Thumb.jpg","unit":"140გრ","category_slug":"canned_goods","parent_category_slug":"groceries","original_price":9.5,"sale_price":9.5,"discount_percent":0.0,"is_on_sale":false,"effective_price":9.5,"chain_rank":4}],"summary":{"avg_price":9.5,"min_price":9.5,"max_price":9.5,"price_spread":0.0,"store_count":1,"promo_count":0,"promo_rate":0.0,"cheapest_brand_id":"agrohub","top_brand_id":"agrohub","model_source":"static-export-live-retail-prices"},"observed_source":"heuristic"}