{"barcode":"4860117330782","display_name":"ბრენდი VSOP 05 ლ, მუყაოს სასაჩუქრე ყუთში","unit":"05 ლ","image_url":"/product-images/shefisu/4730.jpg","category_slug":"juice_nectar","parent_category_slug":"drinks","offers":[{"store_slug":"shefisu","store_name":"Shefisu","brand_id":"shefisu","name":"ბრენდი VSOP 05 ლ, მუყაოს სასაჩუქრე ყუთში","barcode":"4860117330782","image_url":"/product-images/shefisu/4730.jpg","unit":"05 ლ","category_slug":"juice_nectar","parent_category_slug":"drinks","original_price":31.5,"sale_price":31.5,"discount_percent":0.0,"is_on_sale":false,"effective_price":31.5,"chain_rank":17},{"store_slug":"carrefour","store_name":"Carrefour","brand_id":"carrefour","name":"რთველისი ბრენდი VSOP 0.5","barcode":"4860117330782","image_url":"https://images.europroduct.ge/prod/9ffc0fd75f/4860117330782.png?w=500","unit":"1 ც","category_slug":"juice_nectar","parent_category_slug":"drinks","original_price":62.95,"sale_price":47.99,"discount_percent":23.76,"is_on_sale":true,"effective_price":47.99,"chain_rank":1},{"store_slug":"europroduct","store_name":"Europroduct","brand_id":"europroduct","name":"რთველისი ბრენდი VSOP 0.5","barcode":"4860117330782","image_url":"https://images.europroduct.ge/prod/9ffc0fd75f/4860117330782.png?w=500","unit":"1 ც","category_slug":"juice_nectar","parent_category_slug":"drinks","original_price":68.0,"sale_price":51.99,"discount_percent":23.54,"is_on_sale":true,"effective_price":51.99,"chain_rank":5}],"summary":{"avg_price":43.83,"min_price":31.5,"max_price":51.99,"price_spread":20.49,"store_count":3,"promo_count":2,"promo_rate":66.7,"cheapest_brand_id":"shefisu","top_brand_id":"carrefour","model_source":"static-export-live-retail-prices"},"observed_source":"heuristic"}