{"barcode":"4860053012032","display_name":"კონიაკი /ასკანელი 5*/ 0.5ლ","unit":"0.5ლ","image_url":"https://images.europroduct.ge/prod/5a4b89f56b/4860053012032.jpg?w=500","category_slug":"private_label","parent_category_slug":"groceries","offers":[{"store_slug":"europroduct","store_name":"Europroduct","brand_id":"europroduct","name":"კონიაკი /ასკანელი 5*/ 0.5ლ","barcode":"4860053012032","image_url":"https://images.europroduct.ge/prod/5a4b89f56b/4860053012032.jpg?w=500","unit":"0.5ლ","category_slug":"private_label","parent_category_slug":"groceries","original_price":40.0,"sale_price":19.99,"discount_percent":50.03,"is_on_sale":true,"effective_price":19.99,"chain_rank":5},{"store_slug":"carrefour","store_name":"Carrefour","brand_id":"carrefour","name":"კონიაკი /ასკანელი 5*/ 0.5ლ","barcode":"4860053012032","image_url":"https://images.europroduct.ge/prod/5a4b89f56b/4860053012032.jpg?w=500","unit":"0.5ლ","category_slug":"private_label","parent_category_slug":"groceries","original_price":32.95,"sale_price":32.95,"discount_percent":0.0,"is_on_sale":false,"effective_price":32.95,"chain_rank":1},{"store_slug":"magniti","store_name":"Magniti","brand_id":"magniti","name":"კონიაკი /ასკანელი 5*/ 0.5ლ","barcode":"4860053012032","image_url":"https://images.europroduct.ge/prod/5a4b89f56b/4860053012032.jpg?w=500","unit":"0.5ლ","category_slug":"private_label","parent_category_slug":"groceries","original_price":32.95,"sale_price":32.95,"discount_percent":0.0,"is_on_sale":false,"effective_price":32.95,"chain_rank":7},{"store_slug":"zgapari","store_name":"Zgapari","brand_id":"zgapari","name":"კონიაკი /ასკანელი 5*/ 0.5ლ","barcode":"4860053012032","image_url":"https://images.europroduct.ge/prod/5a4b89f56b/4860053012032.jpg?w=500","unit":"0.5ლ","category_slug":"private_label","parent_category_slug":"groceries","original_price":33.95,"sale_price":33.95,"discount_percent":0.0,"is_on_sale":false,"effective_price":33.95,"chain_rank":9},{"store_slug":"alcorium","store_name":"Alcorium","brand_id":"alcorium","name":"კონიაკი /ასკანელი 5*/ 0.5ლ","barcode":"4860053012032","image_url":"https://images.europroduct.ge/prod/5a4b89f56b/4860053012032.jpg?w=500","unit":"0.5ლ","category_slug":"private_label","parent_category_slug":"groceries","original_price":35.4,"sale_price":35.4,"discount_percent":0.0,"is_on_sale":false,"effective_price":35.4,"chain_rank":16}],"summary":{"avg_price":31.05,"min_price":19.99,"max_price":35.4,"price_spread":15.41,"store_count":5,"promo_count":1,"promo_rate":20.0,"cheapest_brand_id":"europroduct","top_brand_id":"alcorium","model_source":"static-export-live-retail-prices"},"observed_source":"heuristic"}