{"barcode":"4860111811829","display_name":"რომაული პომიდორი 650 გრ","unit":"650 გრ","image_url":"https://static.agrohub.lemon.do/Agrohub_files/cabe217a-d5a9-4c89-8717-de3b29a7868c_Thumb.jpg","category_slug":"private_label","parent_category_slug":"groceries","offers":[{"store_slug":"agrohub","store_name":"Agrohub","brand_id":"agrohub","name":"რომაული პომიდორი 650 გრ","barcode":"4860111811829","image_url":"https://static.agrohub.lemon.do/Agrohub_files/cabe217a-d5a9-4c89-8717-de3b29a7868c_Thumb.jpg","unit":"650 გრ","category_slug":"private_label","parent_category_slug":"groceries","original_price":3.55,"sale_price":3.55,"discount_percent":0.0,"is_on_sale":false,"effective_price":3.55,"chain_rank":4},{"store_slug":"nikora","store_name":"Nikora","brand_id":"nikora","name":"რომაული პომიდორი 650 გრ","barcode":"4860111811829","image_url":"https://static.agrohub.lemon.do/Agrohub_files/cabe217a-d5a9-4c89-8717-de3b29a7868c_Thumb.jpg","unit":"650 გრ","category_slug":"private_label","parent_category_slug":"groceries","original_price":3.7,"sale_price":3.7,"discount_percent":0.0,"is_on_sale":false,"effective_price":3.7,"chain_rank":6}],"summary":{"avg_price":3.62,"min_price":3.55,"max_price":3.7,"price_spread":0.15,"store_count":2,"promo_count":0,"promo_rate":0.0,"cheapest_brand_id":"agrohub","top_brand_id":"agrohub","model_source":"static-export-live-retail-prices"},"observed_source":"heuristic"}