{"barcode":"4860101960971","display_name":"სუპრემო ყვითელი ტყემალი 330 გრ/4860101960971 1ც","unit":"330 გრ","image_url":"https://imageproxy.wolt.com/assets/6a29631de96e3b62fd706dc5","category_slug":"frozen","parent_category_slug":"frozen","offers":[{"store_slug":"carrefour","store_name":"Carrefour","brand_id":"carrefour","name":"სუპრემო ყვითელი ტყემალი 330 გრ/4860101960971 1ც","barcode":"4860101960971","image_url":"https://imageproxy.wolt.com/assets/6a29631de96e3b62fd706dc5","unit":"330 გრ","category_slug":"frozen","parent_category_slug":"frozen","original_price":6.95,"sale_price":5.49,"discount_percent":21.01,"is_on_sale":true,"effective_price":5.49,"chain_rank":1}],"summary":{"avg_price":5.49,"min_price":5.49,"max_price":5.49,"price_spread":0.0,"store_count":1,"promo_count":1,"promo_rate":100.0,"cheapest_brand_id":"carrefour","top_brand_id":"carrefour","model_source":"static-export-live-retail-prices"},"observed_source":"heuristic"}