{"barcode":"4860109190196","display_name":"ღვინო / საფერავი, / წითელი, მშრალი,/  0,75, GS / 2023","unit":null,"image_url":"https://images.europroduct.ge/prod/aa9d8a88b1/4860109190196.png?w=500","category_slug":"juice_nectar","parent_category_slug":"drinks","offers":[{"store_slug":"europroduct","store_name":"Europroduct","brand_id":"europroduct","name":"ღვინო / საფერავი, / წითელი, მშრალი,/  0,75, GS / 2023","barcode":"4860109190196","image_url":"https://images.europroduct.ge/prod/aa9d8a88b1/4860109190196.png?w=500","unit":null,"category_slug":"juice_nectar","parent_category_slug":"drinks","original_price":11.5,"sale_price":11.5,"discount_percent":0.0,"is_on_sale":false,"effective_price":11.5,"chain_rank":5}],"summary":{"avg_price":11.5,"min_price":11.5,"max_price":11.5,"price_spread":0.0,"store_count":1,"promo_count":0,"promo_rate":0.0,"cheapest_brand_id":"europroduct","top_brand_id":"europroduct","model_source":"static-export-live-retail-prices"},"observed_source":"heuristic"}