{"barcode":"4860123240013","display_name":"სოკო შიიტაკე /250გრ /","unit":"250გრ","image_url":"https://static.agrohub.lemon.do/Agrohub_files/004f71c3-36cc-423c-9106-49ef35b4c8b7_Thumb.jpg","category_slug":"other","parent_category_slug":"other","offers":[{"store_slug":"agrohub","store_name":"Agrohub","brand_id":"agrohub","name":"სოკო შიიტაკე /250გრ /","barcode":"4860123240013","image_url":"https://static.agrohub.lemon.do/Agrohub_files/004f71c3-36cc-423c-9106-49ef35b4c8b7_Thumb.jpg","unit":"250გრ","category_slug":"other","parent_category_slug":"other","original_price":14.5,"sale_price":14.5,"discount_percent":0.0,"is_on_sale":false,"effective_price":14.5,"chain_rank":4}],"summary":{"avg_price":14.5,"min_price":14.5,"max_price":14.5,"price_spread":0.0,"store_count":1,"promo_count":0,"promo_rate":0.0,"cheapest_brand_id":"agrohub","top_brand_id":"agrohub","model_source":"static-export-live-retail-prices"},"observed_source":"heuristic"}