{"barcode":"4860108990964","display_name":"ორგანული ბრინჯი ბასმათი თეთრი ნატურალისი 600 გ.","unit":"600 გ","image_url":"https://static.agrohub.lemon.do/Agrohub_files/3f1f0a6e-a037-43c2-8b44-75144335fd8f_Thumb.jpg","category_slug":"cereals","parent_category_slug":"groceries","offers":[{"store_slug":"europroduct","store_name":"Europroduct","brand_id":"europroduct","name":"ორგანული ბრინჯი ბასმათი თეთრი ნატურალისი 600 გ.","barcode":"4860108990964","image_url":"https://static.agrohub.lemon.do/Agrohub_files/3f1f0a6e-a037-43c2-8b44-75144335fd8f_Thumb.jpg","unit":"600 გ","category_slug":"cereals","parent_category_slug":"groceries","original_price":14.95,"sale_price":12.99,"discount_percent":13.11,"is_on_sale":true,"effective_price":12.99,"chain_rank":5},{"store_slug":"agrohub","store_name":"Agrohub","brand_id":"agrohub","name":"ორგანული ბრინჯი ბასმათი თეთრი ნატურალისი 600 გ.","barcode":"4860108990964","image_url":"https://static.agrohub.lemon.do/Agrohub_files/3f1f0a6e-a037-43c2-8b44-75144335fd8f_Thumb.jpg","unit":"600 გ","category_slug":"cereals","parent_category_slug":"groceries","original_price":15.95,"sale_price":15.95,"discount_percent":0.0,"is_on_sale":false,"effective_price":15.95,"chain_rank":4}],"summary":{"avg_price":14.47,"min_price":12.99,"max_price":15.95,"price_spread":2.96,"store_count":2,"promo_count":1,"promo_rate":50.0,"cheapest_brand_id":"europroduct","top_brand_id":"agrohub","model_source":"static-export-live-retail-prices"},"observed_source":"heuristic"}