{"barcode":"4860101960186","display_name":"მაკარონი /სუპრემო/ 400გრ","unit":"400გრ","image_url":"https://imageproxy.wolt.com/assets/68e8ae8a76f0377a07cbc338","category_slug":"frozen","parent_category_slug":"frozen","offers":[{"store_slug":"magniti","store_name":"Magniti","brand_id":"magniti","name":"მაკარონი /სუპრემო/ 400გრ","barcode":"4860101960186","image_url":"https://imageproxy.wolt.com/assets/68e8ae8a76f0377a07cbc338","unit":"400გრ","category_slug":"frozen","parent_category_slug":"frozen","original_price":3.25,"sale_price":3.25,"discount_percent":0.0,"is_on_sale":false,"effective_price":3.25,"chain_rank":7}],"summary":{"avg_price":3.25,"min_price":3.25,"max_price":3.25,"price_spread":0.0,"store_count":1,"promo_count":0,"promo_rate":0.0,"cheapest_brand_id":"magniti","top_brand_id":"magniti","model_source":"static-export-live-retail-prices"},"observed_source":"heuristic"}