{"barcode":"4860103350114","display_name":"ლიმონათი / ზედაზენი ტარხუნა / 2ლ პეტი","unit":"2ლ","image_url":"https://static.agrohub.lemon.do/Agrohub_files/c90293f0-3fad-4e74-b397-26b53dc1c801_Thumb.jpg","category_slug":"juice_nectar","parent_category_slug":"drinks","offers":[{"store_slug":"spar","store_name":"Spar","brand_id":"spar","name":"ლიმონათი / ზედაზენი ტარხუნა / 2ლ პეტი","barcode":"4860103350114","image_url":"https://static.agrohub.lemon.do/Agrohub_files/c90293f0-3fad-4e74-b397-26b53dc1c801_Thumb.jpg","unit":"2ლ","category_slug":"juice_nectar","parent_category_slug":"drinks","original_price":4.85,"sale_price":2.99,"discount_percent":38.35,"is_on_sale":true,"effective_price":2.99,"chain_rank":3},{"store_slug":"magniti","store_name":"Magniti","brand_id":"magniti","name":"ლიმონათი / ზედაზენი ტარხუნა / 2ლ პეტი","barcode":"4860103350114","image_url":"https://static.agrohub.lemon.do/Agrohub_files/c90293f0-3fad-4e74-b397-26b53dc1c801_Thumb.jpg","unit":"2ლ","category_slug":"juice_nectar","parent_category_slug":"drinks","original_price":4.65,"sale_price":4.65,"discount_percent":0.0,"is_on_sale":false,"effective_price":4.65,"chain_rank":7}],"summary":{"avg_price":3.82,"min_price":2.99,"max_price":4.65,"price_spread":1.66,"store_count":2,"promo_count":1,"promo_rate":50.0,"cheapest_brand_id":"spar","top_brand_id":"magniti","model_source":"static-export-live-retail-prices"},"observed_source":"heuristic"}