{"barcode":"4860038075403","display_name":"ღვინო /თბილღვინო/  ალაზნის ველი წითელი ნ.ტ/ 0.75ლ","unit":"0.75ლ","image_url":"https://imageproxy.wolt.com/assets/69860b2d4fe07fe9e1893ccb","category_slug":"alcohol","parent_category_slug":"drinks","offers":[{"store_slug":"nikora","store_name":"Nikora","brand_id":"nikora","name":"ღვინო /თბილღვინო/  ალაზნის ველი წითელი ნ.ტ/ 0.75ლ","barcode":"4860038075403","image_url":"https://imageproxy.wolt.com/assets/69860b2d4fe07fe9e1893ccb","unit":"0.75ლ","category_slug":"alcohol","parent_category_slug":"drinks","original_price":15.5,"sale_price":15.5,"discount_percent":0.0,"is_on_sale":false,"effective_price":15.5,"chain_rank":6},{"store_slug":"carrefour","store_name":"Carrefour","brand_id":"carrefour","name":"ღვინო /თბილღვინო/  ალაზნის ველი წითელი ნ.ტ/ 0.75ლ","barcode":"4860038075403","image_url":"https://imageproxy.wolt.com/assets/69860b2d4fe07fe9e1893ccb","unit":"0.75ლ","category_slug":"alcohol","parent_category_slug":"drinks","original_price":16.95,"sale_price":16.95,"discount_percent":0.0,"is_on_sale":false,"effective_price":16.95,"chain_rank":1}],"summary":{"avg_price":16.23,"min_price":15.5,"max_price":16.95,"price_spread":1.45,"store_count":2,"promo_count":0,"promo_rate":0.0,"cheapest_brand_id":"nikora","top_brand_id":"carrefour","model_source":"static-export-live-retail-prices"},"observed_source":"heuristic"}