{"barcode":"4860006060042","display_name":"პური \"იფქლი დიღომი\" ცეხვილი 510გრ","unit":"510გრ","image_url":"https://static.goodwill.ge/Goodwill_files/2df20632-19ae-43f3-8d83-9732d38e4a5b_Thumb.jpg","category_slug":"bakery","parent_category_slug":"bakery","offers":[{"store_slug":"2nabiji","store_name":"2 Nabiji","brand_id":"2nabiji","name":"პური \"იფქლი დიღომი\" ცეხვილი 510გრ","barcode":"4860006060042","image_url":"https://static.goodwill.ge/Goodwill_files/2df20632-19ae-43f3-8d83-9732d38e4a5b_Thumb.jpg","unit":"510გრ","category_slug":"bakery","parent_category_slug":"bakery","original_price":1.4,"sale_price":1.4,"discount_percent":0.0,"is_on_sale":false,"effective_price":1.4,"chain_rank":8}],"summary":{"avg_price":1.4,"min_price":1.4,"max_price":1.4,"price_spread":0.0,"store_count":1,"promo_count":0,"promo_rate":0.0,"cheapest_brand_id":"2nabiji","top_brand_id":"2nabiji","model_source":"static-export-live-retail-prices"},"observed_source":"heuristic"}