{"barcode":"4860004390080","display_name":"პური/სვეიკეტა ლიტვური/375გრ","unit":"375გრ","image_url":"https://static.agrohub.lemon.do/Agrohub_files/f295feaf-a7da-44e7-9b52-983e2fbdb52a_Thumb.jpg","category_slug":"bakery","parent_category_slug":"bakery","offers":[{"store_slug":"2nabiji","store_name":"2 Nabiji","brand_id":"2nabiji","name":"პური/სვეიკეტა ლიტვური/375გრ","barcode":"4860004390080","image_url":"https://static.agrohub.lemon.do/Agrohub_files/f295feaf-a7da-44e7-9b52-983e2fbdb52a_Thumb.jpg","unit":"375გრ","category_slug":"bakery","parent_category_slug":"bakery","original_price":2.25,"sale_price":2.25,"discount_percent":0.0,"is_on_sale":false,"effective_price":2.25,"chain_rank":8},{"store_slug":"magniti","store_name":"Magniti","brand_id":"magniti","name":"პური/სვეიკეტა ლიტვური/375გრ","barcode":"4860004390080","image_url":"https://static.agrohub.lemon.do/Agrohub_files/f295feaf-a7da-44e7-9b52-983e2fbdb52a_Thumb.jpg","unit":"375გრ","category_slug":"bakery","parent_category_slug":"bakery","original_price":2.3,"sale_price":2.3,"discount_percent":0.0,"is_on_sale":false,"effective_price":2.3,"chain_rank":7}],"summary":{"avg_price":2.27,"min_price":2.25,"max_price":2.3,"price_spread":0.05,"store_count":2,"promo_count":0,"promo_rate":0.0,"cheapest_brand_id":"2nabiji","top_brand_id":"2nabiji","model_source":"static-export-live-retail-prices"},"observed_source":"heuristic"}