{"barcode":"4869002034729","display_name":"\"აის ეიჯი\"- ყინულის კუბები 5x5x5 6ც","unit":"6ც","image_url":"https://static.goodwill.ge/Goodwill_files/ea8de933-00e6-473f-8ee0-930272e80bda_Thumb.jpg","category_slug":"frozen","parent_category_slug":"frozen","offers":[{"store_slug":"carrefour","store_name":"Carrefour","brand_id":"carrefour","name":"\"აის ეიჯი\"- ყინულის კუბები 5x5x5 6ც","barcode":"4869002034729","image_url":"https://static.goodwill.ge/Goodwill_files/ea8de933-00e6-473f-8ee0-930272e80bda_Thumb.jpg","unit":"6ც","category_slug":"frozen","parent_category_slug":"frozen","original_price":7.95,"sale_price":7.95,"discount_percent":0.0,"is_on_sale":false,"effective_price":7.95,"chain_rank":1},{"store_slug":"goodwill","store_name":"Goodwill","brand_id":"goodwill","name":"\"აის ეიჯი\"- ყინულის კუბები 5x5x5 6ც","barcode":"4869002034729","image_url":"https://static.goodwill.ge/Goodwill_files/ea8de933-00e6-473f-8ee0-930272e80bda_Thumb.jpg","unit":"6ც","category_slug":"frozen","parent_category_slug":"frozen","original_price":12.95,"sale_price":12.95,"discount_percent":0.0,"is_on_sale":false,"effective_price":12.95,"chain_rank":2}],"summary":{"avg_price":10.45,"min_price":7.95,"max_price":12.95,"price_spread":5.0,"store_count":2,"promo_count":0,"promo_rate":0.0,"cheapest_brand_id":"carrefour","top_brand_id":"carrefour","model_source":"static-export-live-retail-prices"},"observed_source":"heuristic"}