{"barcode":"5000299225004","display_name":"CHIVAS REGAL\\40% 18 წლიანი  0,7 - ვისკი, ჩივას რეგალი,","unit":"1 ც","image_url":"https://static.agrohub.lemon.do/Agrohub_files/dd26674e-41d5-4d10-8f13-78e7eb56e8ef_Thumb.jpg","category_slug":"juice_nectar","parent_category_slug":"drinks","offers":[{"store_slug":"carrefour","store_name":"Carrefour","brand_id":"carrefour","name":"CHIVAS REGAL\\40% 18 წლიანი  0,7 - ვისკი, ჩივას რეგალი,","barcode":"5000299225004","image_url":"https://static.agrohub.lemon.do/Agrohub_files/dd26674e-41d5-4d10-8f13-78e7eb56e8ef_Thumb.jpg","unit":"1 ც","category_slug":"juice_nectar","parent_category_slug":"drinks","original_price":319.9,"sale_price":319.9,"discount_percent":0.0,"is_on_sale":false,"effective_price":319.9,"chain_rank":1},{"store_slug":"agrohub","store_name":"Agrohub","brand_id":"agrohub","name":"CHIVAS REGAL\\40% 18 წლიანი  0,7 - ვისკი, ჩივას რეგალი,","barcode":"5000299225004","image_url":"https://static.agrohub.lemon.do/Agrohub_files/dd26674e-41d5-4d10-8f13-78e7eb56e8ef_Thumb.jpg","unit":"1 ც","category_slug":"juice_nectar","parent_category_slug":"drinks","original_price":319.9,"sale_price":319.9,"discount_percent":0.0,"is_on_sale":false,"effective_price":319.9,"chain_rank":4},{"store_slug":"goodwill","store_name":"Goodwill","brand_id":"goodwill","name":"CHIVAS REGAL\\40% 18 წლიანი  0,7 - ვისკი, ჩივას რეგალი,","barcode":"5000299225004","image_url":"https://static.agrohub.lemon.do/Agrohub_files/dd26674e-41d5-4d10-8f13-78e7eb56e8ef_Thumb.jpg","unit":"1 ც","category_slug":"juice_nectar","parent_category_slug":"drinks","original_price":329.8,"sale_price":329.8,"discount_percent":0.0,"is_on_sale":false,"effective_price":329.8,"chain_rank":2}],"summary":{"avg_price":323.2,"min_price":319.9,"max_price":329.8,"price_spread":9.9,"store_count":3,"promo_count":0,"promo_rate":0.0,"cheapest_brand_id":"carrefour","top_brand_id":"agrohub","model_source":"static-export-live-retail-prices"},"observed_source":"heuristic"}