{"barcode":"5010196023313","display_name":"ვისკი \"კლეიმორი\" 40% 700 მლ / 5010196023313","unit":"700 მლ","image_url":"https://imageproxy.wolt.com/assets/695f74aa480a5d9363757213","category_slug":"alcohol","parent_category_slug":"drinks","offers":[{"store_slug":"magniti","store_name":"Magniti","brand_id":"magniti","name":"ვისკი \"კლეიმორი\" 40% 700 მლ / 5010196023313","barcode":"5010196023313","image_url":"https://imageproxy.wolt.com/assets/695f74aa480a5d9363757213","unit":"700 მლ","category_slug":"alcohol","parent_category_slug":"drinks","original_price":44.95,"sale_price":44.95,"discount_percent":0.0,"is_on_sale":false,"effective_price":44.95,"chain_rank":7}],"summary":{"avg_price":44.95,"min_price":44.95,"max_price":44.95,"price_spread":0.0,"store_count":1,"promo_count":0,"promo_rate":0.0,"cheapest_brand_id":"magniti","top_brand_id":"magniti","model_source":"static-export-live-retail-prices"},"observed_source":"heuristic"}