{"barcode":"5201360543205","display_name":"კრუასანი /7DAYS  მინი კაკაოთი /185გრ","unit":"185გრ","image_url":"https://static.agrohub.lemon.do/Agrohub_files/aeed639b-473f-4421-984b-6624fd0add7a_Thumb.jpg","category_slug":"bakery","parent_category_slug":"bakery","offers":[{"store_slug":"agrohub","store_name":"Agrohub","brand_id":"agrohub","name":"კრუასანი /7DAYS  მინი კაკაოთი /185გრ","barcode":"5201360543205","image_url":"https://static.agrohub.lemon.do/Agrohub_files/aeed639b-473f-4421-984b-6624fd0add7a_Thumb.jpg","unit":"185გრ","category_slug":"bakery","parent_category_slug":"bakery","original_price":7.7,"sale_price":5.5,"discount_percent":28.57,"is_on_sale":true,"effective_price":5.5,"chain_rank":4},{"store_slug":"goodwill","store_name":"Goodwill","brand_id":"goodwill","name":"კრუასანი /7DAYS  მინი კაკაოთი /185გრ","barcode":"5201360543205","image_url":"https://static.agrohub.lemon.do/Agrohub_files/aeed639b-473f-4421-984b-6624fd0add7a_Thumb.jpg","unit":"185გრ","category_slug":"bakery","parent_category_slug":"bakery","original_price":7.8,"sale_price":7.8,"discount_percent":0.0,"is_on_sale":false,"effective_price":7.8,"chain_rank":2}],"summary":{"avg_price":6.65,"min_price":5.5,"max_price":7.8,"price_spread":2.3,"store_count":2,"promo_count":1,"promo_rate":50.0,"cheapest_brand_id":"agrohub","top_brand_id":"agrohub","model_source":"static-export-live-retail-prices"},"observed_source":"heuristic"}