{"barcode":"5411188112709","display_name":"სასმელი ნუშის  შაქრის გარეშე /ალპრო/ 1ლ","unit":"1ლ","image_url":"https://static.agrohub.lemon.do/Agrohub_files/4115219d-4a88-4240-a636-c5dbb2df1440_Thumb.jpg","category_slug":"eggs","parent_category_slug":"dairy","offers":[{"store_slug":"agrohub","store_name":"Agrohub","brand_id":"agrohub","name":"სასმელი ნუშის  შაქრის გარეშე /ალპრო/ 1ლ","barcode":"5411188112709","image_url":"https://static.agrohub.lemon.do/Agrohub_files/4115219d-4a88-4240-a636-c5dbb2df1440_Thumb.jpg","unit":"1ლ","category_slug":"eggs","parent_category_slug":"dairy","original_price":13.95,"sale_price":13.95,"discount_percent":0.0,"is_on_sale":false,"effective_price":13.95,"chain_rank":4}],"summary":{"avg_price":13.95,"min_price":13.95,"max_price":13.95,"price_spread":0.0,"store_count":1,"promo_count":0,"promo_rate":0.0,"cheapest_brand_id":"agrohub","top_brand_id":"agrohub","model_source":"static-export-live-retail-prices"},"observed_source":"heuristic"}