{"barcode":"5900512300559","display_name":"ნაღები 36 % /mlekovita/ 1 ლ","unit":"1 ლ","image_url":"https://static.agrohub.lemon.do/Agrohub_files/5e81d5f3-5177-4a0b-bde7-6aee4d203608_Thumb.jpg","category_slug":"eggs","parent_category_slug":"dairy","offers":[{"store_slug":"agrohub","store_name":"Agrohub","brand_id":"agrohub","name":"ნაღები 36 % /mlekovita/ 1 ლ","barcode":"5900512300559","image_url":"https://static.agrohub.lemon.do/Agrohub_files/5e81d5f3-5177-4a0b-bde7-6aee4d203608_Thumb.jpg","unit":"1 ლ","category_slug":"eggs","parent_category_slug":"dairy","original_price":32.0,"sale_price":32.0,"discount_percent":0.0,"is_on_sale":false,"effective_price":32.0,"chain_rank":4}],"summary":{"avg_price":32.0,"min_price":32.0,"max_price":32.0,"price_spread":0.0,"store_count":1,"promo_count":0,"promo_rate":0.0,"cheapest_brand_id":"agrohub","top_brand_id":"agrohub","model_source":"static-export-live-retail-prices"},"observed_source":"heuristic"}