{"barcode":"5941194000382","display_name":"მარილიანი ჩხირი \"კროკო\" გრძელი 250გრ","unit":"250გრ","image_url":"https://static.agrohub.lemon.do/Agrohub_files/96ff4f38-ddae-44f5-ba8a-4b8502cd696d_Thumb.jpg","category_slug":"milk_kefir","parent_category_slug":"dairy","offers":[{"store_slug":"2nabiji","store_name":"Kalata","brand_id":"2nabiji","name":"მარილიანი ჩხირი \"კროკო\" გრძელი 250გრ","barcode":"5941194000382","image_url":"https://static.agrohub.lemon.do/Agrohub_files/96ff4f38-ddae-44f5-ba8a-4b8502cd696d_Thumb.jpg","unit":"250გრ","category_slug":"milk_kefir","parent_category_slug":"dairy","original_price":4.49,"sale_price":3.99,"discount_percent":11.14,"is_on_sale":true,"effective_price":3.99,"chain_rank":8},{"store_slug":"magniti","store_name":"Magniti","brand_id":"magniti","name":"მარილიანი ჩხირი \"კროკო\" გრძელი 250გრ","barcode":"5941194000382","image_url":"https://static.agrohub.lemon.do/Agrohub_files/96ff4f38-ddae-44f5-ba8a-4b8502cd696d_Thumb.jpg","unit":"250გრ","category_slug":"milk_kefir","parent_category_slug":"dairy","original_price":5.5,"sale_price":5.5,"discount_percent":0.0,"is_on_sale":false,"effective_price":5.5,"chain_rank":7}],"summary":{"avg_price":4.75,"min_price":3.99,"max_price":5.5,"price_spread":1.51,"store_count":2,"promo_count":1,"promo_rate":50.0,"cheapest_brand_id":"2nabiji","top_brand_id":"2nabiji","model_source":"static-export-live-retail-prices"},"observed_source":"heuristic"}