{"barcode":"6408432000065","display_name":"ნაღების კრემყველი /ვალიო/ კლასიკური, ულაქტოზო  8*180გრ","unit":"180გრ","image_url":"https://static.agrohub.lemon.do/Agrohub_files/19705e8c-f35a-4cb1-bfbf-2dd7a3a1c35c_Thumb.jpg","category_slug":"cheese","parent_category_slug":"dairy","offers":[{"store_slug":"carrefour","store_name":"Carrefour","brand_id":"carrefour","name":"ნაღების კრემყველი /ვალიო/ კლასიკური, ულაქტოზო  8*180გრ","barcode":"6408432000065","image_url":"https://static.agrohub.lemon.do/Agrohub_files/19705e8c-f35a-4cb1-bfbf-2dd7a3a1c35c_Thumb.jpg","unit":"180გრ","category_slug":"cheese","parent_category_slug":"dairy","original_price":12.5,"sale_price":6.57,"discount_percent":47.44,"is_on_sale":true,"effective_price":6.57,"chain_rank":1},{"store_slug":"europroduct","store_name":"Europroduct","brand_id":"europroduct","name":"ნაღების კრემყველი /ვალიო/ კლასიკური, ულაქტოზო  8*180გრ","barcode":"6408432000065","image_url":"https://static.agrohub.lemon.do/Agrohub_files/19705e8c-f35a-4cb1-bfbf-2dd7a3a1c35c_Thumb.jpg","unit":"180გრ","category_slug":"cheese","parent_category_slug":"dairy","original_price":10.95,"sale_price":6.99,"discount_percent":36.16,"is_on_sale":true,"effective_price":6.99,"chain_rank":5},{"store_slug":"agrohub","store_name":"Agrohub","brand_id":"agrohub","name":"ნაღების კრემყველი /ვალიო/ კლასიკური, ულაქტოზო  8*180გრ","barcode":"6408432000065","image_url":"https://static.agrohub.lemon.do/Agrohub_files/19705e8c-f35a-4cb1-bfbf-2dd7a3a1c35c_Thumb.jpg","unit":"180გრ","category_slug":"cheese","parent_category_slug":"dairy","original_price":11.95,"sale_price":9.95,"discount_percent":16.74,"is_on_sale":true,"effective_price":9.95,"chain_rank":4},{"store_slug":"goodwill","store_name":"Goodwill","brand_id":"goodwill","name":"ნაღების კრემყველი /ვალიო/ კლასიკური, ულაქტოზო  8*180გრ","barcode":"6408432000065","image_url":"https://static.agrohub.lemon.do/Agrohub_files/19705e8c-f35a-4cb1-bfbf-2dd7a3a1c35c_Thumb.jpg","unit":"180გრ","category_slug":"cheese","parent_category_slug":"dairy","original_price":12.75,"sale_price":12.75,"discount_percent":0.0,"is_on_sale":false,"effective_price":12.75,"chain_rank":2}],"summary":{"avg_price":9.06,"min_price":6.57,"max_price":12.75,"price_spread":6.18,"store_count":4,"promo_count":3,"promo_rate":75.0,"cheapest_brand_id":"carrefour","top_brand_id":"agrohub","model_source":"static-export-live-retail-prices"},"observed_source":"heuristic"}