{"barcode":"8001100011899","display_name":"რძიანი ორცხობილა /ბალოკკო/ შაქრის ნატეხებით 12*350გ","unit":"350გ","image_url":"https://images.europroduct.ge/prod/b046ea7b14/8001100011899.jpg?w=500","category_slug":"milk_kefir","parent_category_slug":"dairy","offers":[{"store_slug":"europroduct","store_name":"Europroduct","brand_id":"europroduct","name":"რძიანი ორცხობილა /ბალოკკო/ შაქრის ნატეხებით 12*350გ","barcode":"8001100011899","image_url":"https://images.europroduct.ge/prod/b046ea7b14/8001100011899.jpg?w=500","unit":"350გ","category_slug":"milk_kefir","parent_category_slug":"dairy","original_price":9.85,"sale_price":6.99,"discount_percent":29.04,"is_on_sale":true,"effective_price":6.99,"chain_rank":5}],"summary":{"avg_price":6.99,"min_price":6.99,"max_price":6.99,"price_spread":0.0,"store_count":1,"promo_count":1,"promo_rate":100.0,"cheapest_brand_id":"europroduct","top_brand_id":"europroduct","model_source":"static-export-live-retail-prices"},"observed_source":"heuristic"}