{"barcode":"8001090894878","display_name":"H&S შამპუნი ქერტლის საწინააღმდეგო","unit":null,"image_url":"https://static.goodwill.ge/Goodwill_files/c2aa9908-36ae-4c5d-8d26-335f8596d1d0_Thumb.jpg","category_slug":"private_label","parent_category_slug":"groceries","offers":[{"store_slug":"goodwill","store_name":"Goodwill","brand_id":"goodwill","name":"H&S შამპუნი ქერტლის საწინააღმდეგო","barcode":"8001090894878","image_url":"https://static.goodwill.ge/Goodwill_files/c2aa9908-36ae-4c5d-8d26-335f8596d1d0_Thumb.jpg","unit":null,"category_slug":"private_label","parent_category_slug":"groceries","original_price":29.95,"sale_price":29.95,"discount_percent":0.0,"is_on_sale":false,"effective_price":29.95,"chain_rank":2}],"summary":{"avg_price":29.95,"min_price":29.95,"max_price":29.95,"price_spread":0.0,"store_count":1,"promo_count":0,"promo_rate":0.0,"cheapest_brand_id":"goodwill","top_brand_id":"goodwill","model_source":"static-export-live-retail-prices"},"observed_source":"heuristic"}