{"barcode":"8004690950098","display_name":"\"La Molisana\"- პესტოს სოუსი მწვანე, ცხარე 190x6","unit":"1 ც","image_url":"https://static.agrohub.lemon.do/Agrohub_files/6d9f5fd6-2ecf-4a74-82df-3536d0b224dd_Thumb.jpg","category_slug":"sauces","parent_category_slug":"groceries","offers":[{"store_slug":"agrohub","store_name":"Agrohub","brand_id":"agrohub","name":"\"La Molisana\"- პესტოს სოუსი მწვანე, ცხარე 190x6","barcode":"8004690950098","image_url":"https://static.agrohub.lemon.do/Agrohub_files/6d9f5fd6-2ecf-4a74-82df-3536d0b224dd_Thumb.jpg","unit":"1 ც","category_slug":"sauces","parent_category_slug":"groceries","original_price":10.7,"sale_price":10.7,"discount_percent":0.0,"is_on_sale":false,"effective_price":10.7,"chain_rank":4},{"store_slug":"goodwill","store_name":"Goodwill","brand_id":"goodwill","name":"\"La Molisana\"- პესტოს სოუსი მწვანე, ცხარე 190x6","barcode":"8004690950098","image_url":"https://static.agrohub.lemon.do/Agrohub_files/6d9f5fd6-2ecf-4a74-82df-3536d0b224dd_Thumb.jpg","unit":"1 ც","category_slug":"sauces","parent_category_slug":"groceries","original_price":10.85,"sale_price":10.85,"discount_percent":0.0,"is_on_sale":false,"effective_price":10.85,"chain_rank":2}],"summary":{"avg_price":10.77,"min_price":10.7,"max_price":10.85,"price_spread":0.15,"store_count":2,"promo_count":0,"promo_rate":0.0,"cheapest_brand_id":"agrohub","top_brand_id":"agrohub","model_source":"static-export-live-retail-prices"},"observed_source":"heuristic"}