{"barcode":"8055186960329","display_name":"კანგაცლილი პომიდორი   2500 გრ  ”Silarus” (იტალია)","unit":"2500 გრ","image_url":"/product-images/shefisu/0803.jpg","category_slug":"canned_goods","parent_category_slug":"groceries","offers":[{"store_slug":"shefisu","store_name":"Shefisu","brand_id":"shefisu","name":"კანგაცლილი პომიდორი   2500 გრ  ”Silarus” (იტალია)","barcode":"8055186960329","image_url":"/product-images/shefisu/0803.jpg","unit":"2500 გრ","category_slug":"canned_goods","parent_category_slug":"groceries","original_price":13.65,"sale_price":13.65,"discount_percent":0.0,"is_on_sale":false,"effective_price":13.65,"chain_rank":17}],"summary":{"avg_price":13.65,"min_price":13.65,"max_price":13.65,"price_spread":0.0,"store_count":1,"promo_count":0,"promo_rate":0.0,"cheapest_brand_id":"shefisu","top_brand_id":"shefisu","model_source":"static-export-live-retail-prices"},"observed_source":"heuristic"}