{"barcode":"8690526734217","display_name":"მარილიანი ჩხირი \"ქრაქსი\" წიწაკით 123გრ","unit":"123გრ","image_url":"https://imageproxy.wolt.com/assets/68e8abf076f0377a07cb9ed9","category_slug":"snacks","parent_category_slug":"snacks","offers":[{"store_slug":"magniti","store_name":"Magniti","brand_id":"magniti","name":"მარილიანი ჩხირი \"ქრაქსი\" წიწაკით 123გრ","barcode":"8690526734217","image_url":"https://imageproxy.wolt.com/assets/68e8abf076f0377a07cb9ed9","unit":"123გრ","category_slug":"snacks","parent_category_slug":"snacks","original_price":3.99,"sale_price":3.99,"discount_percent":0.0,"is_on_sale":false,"effective_price":3.99,"chain_rank":7}],"summary":{"avg_price":3.99,"min_price":3.99,"max_price":3.99,"price_spread":0.0,"store_count":1,"promo_count":0,"promo_rate":0.0,"cheapest_brand_id":"magniti","top_brand_id":"magniti","model_source":"static-export-live-retail-prices"},"observed_source":"heuristic"}