{"barcode":"8690559020714","display_name":"ორაგულის სტეიკი/ Dardanel/ ორაგულის ნაჭრები 10*400გრ","unit":"400გრ","image_url":"https://images.europroduct.ge/prod/37d8b835c9/8690559020714.jpg?w=500","category_slug":"frozen","parent_category_slug":"frozen","offers":[{"store_slug":"europroduct","store_name":"Europroduct","brand_id":"europroduct","name":"ორაგულის სტეიკი/ Dardanel/ ორაგულის ნაჭრები 10*400გრ","barcode":"8690559020714","image_url":"https://images.europroduct.ge/prod/37d8b835c9/8690559020714.jpg?w=500","unit":"400გრ","category_slug":"frozen","parent_category_slug":"frozen","original_price":46.95,"sale_price":46.95,"discount_percent":0.0,"is_on_sale":false,"effective_price":46.95,"chain_rank":5},{"store_slug":"goodwill","store_name":"Goodwill","brand_id":"goodwill","name":"ორაგულის სტეიკი/ Dardanel/ ორაგულის ნაჭრები 10*400გრ","barcode":"8690559020714","image_url":"https://images.europroduct.ge/prod/37d8b835c9/8690559020714.jpg?w=500","unit":"400გრ","category_slug":"frozen","parent_category_slug":"frozen","original_price":55.95,"sale_price":55.95,"discount_percent":0.0,"is_on_sale":false,"effective_price":55.95,"chain_rank":2}],"summary":{"avg_price":51.45,"min_price":46.95,"max_price":55.95,"price_spread":9.0,"store_count":2,"promo_count":0,"promo_rate":0.0,"cheapest_brand_id":"europroduct","top_brand_id":"europroduct","model_source":"static-export-live-retail-prices"},"observed_source":"heuristic"}